uvr/__init__.py
uvr/uvr.py
uvr-0.1.23.dist-info/METADATA
uvr-0.1.23.dist-info/WHEEL
uvr-0.1.23.dist-info/entry_points.txt
uvr-0.1.23.dist-info/RECORD
