Metadata-Version: 2.4
Name: uvr
Version: 0.1.23
Summary: Simple script execution with uv - run Python scripts without explicit --project flag
Project-URL: Homepage, https://github.com/karnigen/uvr
Project-URL: Repository, https://github.com/karnigen/uvr.git
Project-URL: Issues, https://github.com/karnigen/uvr/issues
Author-email: karnigen <karnigen@gmail.com>
License: MIT
Keywords: python,runner,script,tool,uv
Classifier: Development Status :: 4 - Beta
Classifier: Intended Audience :: Developers
Classifier: License :: OSI Approved :: MIT License
Classifier: Programming Language :: Python :: 3
Classifier: Programming Language :: Python :: 3.9
Classifier: Programming Language :: Python :: 3.10
Classifier: Programming Language :: Python :: 3.11
Classifier: Programming Language :: Python :: 3.12
Classifier: Programming Language :: Python :: 3.13
Classifier: Programming Language :: Python :: 3.14
Classifier: Topic :: Software Development :: Build Tools
Requires-Python: >=3.9
